{
  "type": "FeatureCollection",
  "features": [
    {
      "type": "Feature",
      "geometry": {
        "type": "Point",
        "coordinates": [
          3.19,
          51.33,
          5
        ]
      },
      "properties": {
        "location": {
          "name": "Zeebrugge, West Flanders, Flanders, BE",
          "licence": "Data © OpenStreetMap contributors, ODbL 1.0. https://osm.org/copyright"
        },
        "requestPointDistance": 16878.7856,
        "modelRunDate": "2020-09-25T18:00Z",
        "timeSeries": [
          {
            "time": "2020-09-25T18:00Z",
            "maxScreenAirTemp": 11.86661,
            "minScreenAirTemp": 11.358247,
            "max10mWindGust": 28.306866,
            "significantWeatherCode": 15,
            "totalPrecipAmount": 2.3098114,
            "totalSnowAmount": 0,
            "windSpeed10m": 20.68,
            "windDirectionFrom10m": 300,
            "windGustSpeed10m": 28.59,
            "visibility": 8430,
            "mslp": 99670,
            "screenRelativeHumidity": 98.66,
            "feelsLikeTemp": 5.61,
            "uvIndex": 0,
            "probOfPrecipitation": 94,
            "probOfSnow": 0,
            "probOfHeavySnow": 0,
            "probOfRain": 94,
            "probOfHeavyRain": 92,
            "probOfHail": 18,
            "probOfSferics": 12
          },
          {
            "time": "2020-09-25T21:00Z",
            "maxScreenAirTemp": 12.487943,
            "minScreenAirTemp": 12.342854,
            "max10mWindGust": 28.923079,
            "significantWeatherCode": 15,
            "totalPrecipAmount": 1.8118943,
            "totalSnowAmount": 0,
            "windSpeed10m": 17.49,
            "windDirectionFrom10m": 314,
            "windGustSpeed10m": 25.21,
            "visibility": 30034,
            "mslp": 99810,
            "screenRelativeHumidity": 83.92,
            "feelsLikeTemp": 6.62,
            "uvIndex": 0,
            "probOfPrecipitation": 92,
            "probOfSnow": 0,
            "probOfHeavySnow": 0,
            "probOfRain": 92,
            "probOfHeavyRain": 91,
            "probOfHail": 19,
            "probOfSferics": 14
          },
          {
            "time": "2020-09-26T00:00Z",
            "maxScreenAirTemp": 12.593297,
            "minScreenAirTemp": 12.357362,
            "max10mWindGust": 28.564085,
            "significantWeatherCode": 15,
            "totalPrecipAmount": 2.1428714,
            "totalSnowAmount": 0,
            "windSpeed10m": 18.029547,
            "windDirectionFrom10m": 313,
            "windGustSpeed10m": 27.290237,
            "visibility": 21248,
            "mslp": 99900,
            "screenRelativeHumidity": 82.561646,
            "feelsLikeTemp": 6.478064,
            "uvIndex": 0,
            "probOfPrecipitation": 92,
            "probOfSnow": 0,
            "probOfHeavySnow": 0,
            "probOfRain": 92,
            "probOfHeavyRain": 90,
            "probOfHail": 19,
            "probOfSferics": 11
          },
          {
            "time": "2020-09-26T03:00Z",
            "maxScreenAirTemp": 12.44637,
            "minScreenAirTemp": 12.372721,
            "max10mWindGust": 26.606829,
            "significantWeatherCode": 30,
            "totalPrecipAmount": 2.1523707,
            "totalSnowAmount": 0,
            "windSpeed10m": 17.527298,
            "windDirectionFrom10m": 313,
            "windGustSpeed10m": 26.572199,
            "visibility": 10291,
            "mslp": 99884,
            "screenRelativeHumidity": 86.961754,
            "feelsLikeTemp": 6.5885515,
            "uvIndex": 1,
            "probOfPrecipitation": 79,
            "probOfSnow": 40,
            "probOfHeavySnow": 30,
            "probOfRain": 79,
            "probOfHeavyRain": 64,
            "probOfHail": 10,
            "probOfSferics": 58
          },
          {
            "time": "2020-09-26T06:00Z",
            "maxScreenAirTemp": 12.7637415,
            "minScreenAirTemp": 12.497822,
            "max10mWindGust": 24.576372,
            "significantWeatherCode": 14,
            "totalPrecipAmount": 4.0370383,
            "totalSnowAmount": 0,
            "windSpeed10m": 14.687992,
            "windDirectionFrom10m": 323,
            "windGustSpeed10m": 22.482756,
            "visibility": 11636,
            "mslp": 100041,
            "screenRelativeHumidity": 82.675255,
            "feelsLikeTemp": 7.4337273,
            "uvIndex": 1,
            "probOfPrecipitation": 69,
            "probOfSnow": 0,
            "probOfHeavySnow": 0,
            "probOfRain": 69,
            "probOfHeavyRain": 67,
            "probOfHail": 14,
            "probOfSferics": 14
          },
          {
            "time": "2020-09-26T09:00Z",
            "maxScreenAirTemp": 12.85839,
            "minScreenAirTemp": 12.54506,
            "max10mWindGust": 22.68447,
            "significantWeatherCode": 15,
            "totalPrecipAmount": 7.3910584,
            "totalSnowAmount": 0,
            "windSpeed10m": 14.064875,
            "windDirectionFrom10m": 326,
            "windGustSpeed10m": 21.857779,
            "visibility": 7518,
            "mslp": 100178,
            "screenRelativeHumidity": 85.86255,
            "feelsLikeTemp": 7.829856,
            "uvIndex": 1,
            "probOfPrecipitation": 83,
            "probOfSnow": 0,
            "probOfHeavySnow": 0,
            "probOfRain": 83,
            "probOfHeavyRain": 81,
            "probOfHail": 17,
            "probOfSferics": 11
          },
          {
            "time": "2020-09-26T12:00Z",
            "maxScreenAirTemp": 13.477373,
            "minScreenAirTemp": 13.090782,
            "max10mWindGust": 22.019169,
            "significantWeatherCode": 14,
            "totalPrecipAmount": 2.6398919,
            "totalSnowAmount": 0,
            "windSpeed10m": 11.003737,
            "windDirectionFrom10m": 328,
            "windGustSpeed10m": 16.877834,
            "visibility": 15968,
            "mslp": 100225,
            "screenRelativeHumidity": 83.5905,
            "feelsLikeTemp": 9.331521,
            "uvIndex": 3,
            "probOfPrecipitation": 65,
            "probOfSnow": 0,
            "probOfHeavySnow": 0,
            "probOfRain": 65,
            "probOfHeavyRain": 63,
            "probOfHail": 14,
            "probOfSferics": 14
          },
          {
            "time": "2020-09-26T15:00Z",
            "maxScreenAirTemp": 14.933327,
            "minScreenAirTemp": 14.775569,
            "max10mWindGust": 19.012342,
            "significantWeatherCode": 10,
            "totalPrecipAmount": 1.4880726,
            "totalSnowAmount": 0,
            "windSpeed10m": 8.055126,
            "windDirectionFrom10m": 342,
            "windGustSpeed10m": 11.804854,
            "visibility": 25293,
            "mslp": 100246,
            "screenRelativeHumidity": 74.34735,
            "feelsLikeTemp": 11.637246,
            "uvIndex": 1,
            "probOfPrecipitation": 40,
            "probOfSnow": 0,
            "probOfHeavySnow": 0,
            "probOfRain": 40,
            "probOfHeavyRain": 25,
            "probOfHail": 3,
            "probOfSferics": 10
          },
          {
            "time": "2020-09-26T18:00Z",
            "maxScreenAirTemp": 14.460466,
            "minScreenAirTemp": 13.859816,
            "max10mWindGust": 17.539686,
            "significantWeatherCode": 15,
            "totalPrecipAmount": 0.9633894,
            "totalSnowAmount": 0,
            "windSpeed10m": 9.051168,
            "windDirectionFrom10m": 350,
            "windGustSpeed10m": 13.72648,
            "visibility": 8860,
            "mslp": 100348,
            "screenRelativeHumidity": 82.33007,
            "feelsLikeTemp": 10.624768,
            "uvIndex": 0,
            "probOfPrecipitation": 82,
            "probOfSnow": 0,
            "probOfHeavySnow": 0,
            "probOfRain": 82,
            "probOfHeavyRain": 79,
            "probOfHail": 16,
            "probOfSferics": 9
          },
          {
            "time": "2020-09-26T21:00Z",
            "maxScreenAirTemp": 15.100729,
            "minScreenAirTemp": 14.843684,
            "max10mWindGust": 18.289291,
            "significantWeatherCode": 15,
            "totalPrecipAmount": 2.8970509,
            "totalSnowAmount": 0,
            "windSpeed10m": 12.399075,
            "windDirectionFrom10m": 351,
            "windGustSpeed10m": 19.107449,
            "visibility": 13529,
            "mslp": 100387,
            "screenRelativeHumidity": 81.15667,
            "feelsLikeTemp": 9.990775,
            "uvIndex": 0,
            "probOfPrecipitation": 84,
            "probOfSnow": 0,
            "probOfHeavySnow": 0,
            "probOfRain": 84,
            "probOfHeavyRain": 79,
            "probOfHail": 16,
            "probOfSferics": 8
          },
          {
            "time": "2020-09-27T00:00Z",
            "maxScreenAirTemp": 14.781558,
            "minScreenAirTemp": 14.515438,
            "max10mWindGust": 19.884457,
            "significantWeatherCode": 15,
            "totalPrecipAmount": 1.4676938,
            "totalSnowAmount": 0,
            "windSpeed10m": 12.933023,
            "windDirectionFrom10m": 344,
            "windGustSpeed10m": 19.885685,
            "visibility": 15816,
            "mslp": 100304,
            "screenRelativeHumidity": 81.753746,
            "feelsLikeTemp": 9.536008,
            "uvIndex": 0,
            "probOfPrecipitation": 89,
            "probOfSnow": 0,
            "probOfHeavySnow": 0,
            "probOfRain": 89,
            "probOfHeavyRain": 84,
            "probOfHail": 16,
            "probOfSferics": 8
          },
          {
            "time": "2020-09-27T03:00Z",
            "maxScreenAirTemp": 14.783877,
            "minScreenAirTemp": 14.606494,
            "max10mWindGust": 22.624374,
            "significantWeatherCode": 15,
            "totalPrecipAmount": 3.8570788,
            "totalSnowAmount": 0,
            "windSpeed10m": 14.281891,
            "windDirectionFrom10m": 345,
            "windGustSpeed10m": 22.095057,
            "visibility": 6383,
            "mslp": 100165,
            "screenRelativeHumidity": 87.311485,
            "feelsLikeTemp": 9.160359,
            "uvIndex": 1,
            "probOfPrecipitation": 91,
            "probOfSnow": 0,
            "probOfHeavySnow": 0,
            "probOfRain": 91,
            "probOfHeavyRain": 88,
            "probOfHail": 18,
            "probOfSferics": 9
          },
          {
            "time": "2020-09-27T06:00Z",
            "maxScreenAirTemp": 15.316045,
            "minScreenAirTemp": 15.026248,
            "max10mWindGust": 23.671482,
            "significantWeatherCode": 15,
            "totalPrecipAmount": 4.3320866,
            "totalSnowAmount": 0,
            "windSpeed10m": 15.063635,
            "windDirectionFrom10m": 349,
            "windGustSpeed10m": 23.535376,
            "visibility": 5102,
            "mslp": 100118,
            "screenRelativeHumidity": 89.85591,
            "feelsLikeTemp": 9.320747,
            "uvIndex": 1,
            "probOfPrecipitation": 92,
            "probOfSnow": 0,
            "probOfHeavySnow": 0,
            "probOfRain": 92,
            "probOfHeavyRain": 90,
            "probOfHail": 18,
            "probOfSferics": 10
          },
          {
            "time": "2020-09-27T09:00Z",
            "maxScreenAirTemp": 16.2807,
            "minScreenAirTemp": 16.19235,
            "max10mWindGust": 21.435867,
            "significantWeatherCode": 15,
            "totalPrecipAmount": 1.9267645,
            "totalSnowAmount": 0,
            "windSpeed10m": 13.261483,
            "windDirectionFrom10m": 3,
            "windGustSpeed10m": 20.80589,
            "visibility": 9003,
            "mslp": 100236,
            "screenRelativeHumidity": 90.64257,
            "feelsLikeTemp": 10.856616,
            "uvIndex": 1,
            "probOfPrecipitation": 86,
            "probOfSnow": 0,
            "probOfHeavySnow": 0,
            "probOfRain": 86,
            "probOfHeavyRain": 82,
            "probOfHail": 16,
            "probOfSferics": 9
          },
          {
            "time": "2020-09-27T12:00Z",
            "maxScreenAirTemp": 17.150183,
            "minScreenAirTemp": 16.671036,
            "max10mWindGust": 19.63407,
            "significantWeatherCode": 12,
            "totalPrecipAmount": 0.7422133,
            "totalSnowAmount": 0,
            "windSpeed10m": 11.258854,
            "windDirectionFrom10m": 6,
            "windGustSpeed10m": 17.535852,
            "visibility": 14746,
            "mslp": 100359,
            "screenRelativeHumidity": 86.98076,
            "feelsLikeTemp": 12.444466,
            "uvIndex": 3,
            "probOfPrecipitation": 55,
            "probOfSnow": 0,
            "probOfHeavySnow": 0,
            "probOfRain": 55,
            "probOfHeavyRain": 34,
            "probOfHail": 3,
            "probOfSferics": 2
          },
          {
            "time": "2020-09-27T15:00Z",
            "maxScreenAirTemp": 17.112188,
            "minScreenAirTemp": 17.03162,
            "max10mWindGust": 16.934746,
            "significantWeatherCode": 12,
            "totalPrecipAmount": 0.6174368,
            "totalSnowAmount": 0,
            "windSpeed10m": 10.244847,
            "windDirectionFrom10m": 7,
            "windGustSpeed10m": 15.969102,
            "visibility": 12773,
            "mslp": 100506,
            "screenRelativeHumidity": 88.25314,
            "feelsLikeTemp": 12.928955,
            "uvIndex": 1,
            "probOfPrecipitation": 52,
            "probOfSnow": 0,
            "probOfHeavySnow": 0,
            "probOfRain": 51,
            "probOfHeavyRain": 27,
            "probOfHail": 1,
            "probOfSferics": 1
          },
          {
            "time": "2020-09-27T18:00Z",
            "maxScreenAirTemp": 16.892452,
            "minScreenAirTemp": 16.534103,
            "max10mWindGust": 15.029164,
            "significantWeatherCode": 12,
            "totalPrecipAmount": 0.48664328,
            "totalSnowAmount": 0,
            "windSpeed10m": 8.480683,
            "windDirectionFrom10m": 9,
            "windGustSpeed10m": 12.651988,
            "visibility": 12532,
            "mslp": 100667,
            "screenRelativeHumidity": 91.63392,
            "feelsLikeTemp": 13.545156,
            "uvIndex": 0,
            "probOfPrecipitation": 54,
            "probOfSnow": 0,
            "probOfHeavySnow": 0,
            "probOfRain": 54,
            "probOfHeavyRain": 36,
            "probOfHail": 4,
            "probOfSferics": 2
          },
          {
            "time": "2020-09-27T21:00Z",
            "maxScreenAirTemp": 16.213968,
            "minScreenAirTemp": 16.145964,
            "max10mWindGust": 12.735995,
            "significantWeatherCode": 12,
            "totalPrecipAmount": 0.5815977,
            "totalSnowAmount": 0,
            "windSpeed10m": 6.8997536,
            "windDirectionFrom10m": 13,
            "windGustSpeed10m": 10.365103,
            "visibility": 13292,
            "mslp": 100799,
            "screenRelativeHumidity": 91.195595,
            "feelsLikeTemp": 13.714569,
            "uvIndex": 0,
            "probOfPrecipitation": 48,
            "probOfSnow": 0,
            "probOfHeavySnow": 0,
            "probOfRain": 48,
            "probOfHeavyRain": 25,
            "probOfHail": 1,
            "probOfSferics": 0
          },
          {
            "time": "2020-09-28T00:00Z",
            "maxScreenAirTemp": 16.334536,
            "minScreenAirTemp": 15.982444,
            "max10mWindGust": 10.922508,
            "significantWeatherCode": 12,
            "totalPrecipAmount": 0.62151873,
            "totalSnowAmount": 0,
            "windSpeed10m": 6.480307,
            "windDirectionFrom10m": 10,
            "windGustSpeed10m": 9.636227,
            "visibility": 11048,
            "mslp": 100842,
            "screenRelativeHumidity": 92.92,
            "feelsLikeTemp": 13.898372,
            "uvIndex": 0,
            "probOfPrecipitation": 52,
            "probOfSnow": 0,
            "probOfHeavySnow": 0,
            "probOfRain": 52,
            "probOfHeavyRain": 34,
            "probOfHail": 3,
            "probOfSferics": 2
          },
          {
            "time": "2020-09-28T03:00Z",
            "maxScreenAirTemp": 16.209343,
            "minScreenAirTemp": 16.143959,
            "max10mWindGust": 11.509041,
            "significantWeatherCode": 8,
            "totalPrecipAmount": 0,
            "totalSnowAmount": 0,
            "windSpeed10m": 6.9628744,
            "windDirectionFrom10m": 351,
            "windGustSpeed10m": 10.446947,
            "visibility": 10091,
            "mslp": 100835,
            "screenRelativeHumidity": 94.29958,
            "feelsLikeTemp": 13.748631,
            "uvIndex": 1,
            "probOfPrecipitation": 17,
            "probOfSnow": 5,
            "probOfHeavySnow": 0,
            "probOfRain": 17,
            "probOfHeavyRain": 6,
            "probOfHail": 0,
            "probOfSferics": 0
          },
          {
            "time": "2020-09-28T06:00Z",
            "maxScreenAirTemp": 16.249584,
            "minScreenAirTemp": 15.984466,
            "max10mWindGust": 12.068704,
            "significantWeatherCode": 8,
            "totalPrecipAmount": 0,
            "totalSnowAmount": 0,
            "windSpeed10m": 7.7087703,
            "windDirectionFrom10m": 341,
            "windGustSpeed10m": 11.622058,
            "visibility": 9722,
            "mslp": 100905,
            "screenRelativeHumidity": 93.94915,
            "feelsLikeTemp": 13.321041,
            "uvIndex": 1,
            "probOfPrecipitation": 16,
            "probOfSnow": 5,
            "probOfHeavySnow": 0,
            "probOfRain": 16,
            "probOfHeavyRain": 5,
            "probOfHail": 0,
            "probOfSferics": 0
          },
          {
            "time": "2020-09-28T09:00Z",
            "maxScreenAirTemp": 16.44097,
            "minScreenAirTemp": 16.271969,
            "max10mWindGust": 12.949456,
            "significantWeatherCode": 7,
            "totalPrecipAmount": 0,
            "totalSnowAmount": 0,
            "windSpeed10m": 8.079684,
            "windDirectionFrom10m": 335,
            "windGustSpeed10m": 12.574067,
            "visibility": 9943,
            "mslp": 101006,
            "screenRelativeHumidity": 91.12175,
            "feelsLikeTemp": 13.4327755,
            "uvIndex": 1,
            "probOfPrecipitation": 17,
            "probOfSnow": 3,
            "probOfHeavySnow": 0,
            "probOfRain": 17,
            "probOfHeavyRain": 7,
            "probOfHail": 1,
            "probOfSferics": 1
          },
          {
            "time": "2020-09-28T12:00Z",
            "maxScreenAirTemp": 16.581985,
            "minScreenAirTemp": 16.124426,
            "max10mWindGust": 13.0759115,
            "significantWeatherCode": 7,
            "totalPrecipAmount": 0,
            "totalSnowAmount": 0,
            "windSpeed10m": 8.032451,
            "windDirectionFrom10m": 319,
            "windGustSpeed10m": 12.668068,
            "visibility": 11465,
            "mslp": 101080,
            "screenRelativeHumidity": 88.09025,
            "feelsLikeTemp": 13.517954,
            "uvIndex": 2,
            "probOfPrecipitation": 14,
            "probOfSnow": 3,
            "probOfHeavySnow": 0,
            "probOfRain": 14,
            "probOfHeavyRain": 5,
            "probOfHail": 0,
            "probOfSferics": 1
          },
          {
            "time": "2020-09-28T15:00Z",
            "maxScreenAirTemp": 16.138784,
            "minScreenAirTemp": 16.060379,
            "max10mWindGust": 13.338662,
            "significantWeatherCode": 7,
            "totalPrecipAmount": 0,
            "totalSnowAmount": 0,
            "windSpeed10m": 7.7506623,
            "windDirectionFrom10m": 315,
            "windGustSpeed10m": 12.0814295,
            "visibility": 15292,
            "mslp": 101137,
            "screenRelativeHumidity": 85.895966,
            "feelsLikeTemp": 13.129544,
            "uvIndex": 1,
            "probOfPrecipitation": 19,
            "probOfSnow": 3,
            "probOfHeavySnow": 0,
            "probOfRain": 19,
            "probOfHeavyRain": 10,
            "probOfHail": 1,
            "probOfSferics": 1
          },
          {
            "time": "2020-09-28T18:00Z",
            "maxScreenAirTemp": 16.001862,
            "minScreenAirTemp": 15.567078,
            "max10mWindGust": 12.111816,
            "significantWeatherCode": 12,
            "totalPrecipAmount": 0.45712343,
            "totalSnowAmount": 0,
            "windSpeed10m": 6.6722393,
            "windDirectionFrom10m": 304,
            "windGustSpeed10m": 10.288822,
            "visibility": 18143,
            "mslp": 101264,
            "screenRelativeHumidity": 84.97513,
            "feelsLikeTemp": 13.150589,
            "uvIndex": 0,
            "probOfPrecipitation": 39,
            "probOfSnow": 0,
            "probOfHeavySnow": 0,
            "probOfRain": 39,
            "probOfHeavyRain": 20,
            "probOfHail": 1,
            "probOfSferics": 0
          },
          {
            "time": "2020-09-28T21:00Z",
            "maxScreenAirTemp": 15.94189,
            "minScreenAirTemp": 15.310915,
            "max10mWindGust": 10.757751,
            "significantWeatherCode": 9,
            "totalPrecipAmount": 0.16377352,
            "totalSnowAmount": 0,
            "windSpeed10m": 6.183937,
            "windDirectionFrom10m": 298,
            "windGustSpeed10m": 9.4915085,
            "visibility": 23143,
            "mslp": 101361,
            "screenRelativeHumidity": 79.22643,
            "feelsLikeTemp": 13.32799,
            "uvIndex": 0,
            "probOfPrecipitation": 28,
            "probOfSnow": 0,
            "probOfHeavySnow": 0,
            "probOfRain": 28,
            "probOfHeavyRain": 15,
            "probOfHail": 1,
            "probOfSferics": 3
          },
          {
            "time": "2020-09-29T00:00Z",
            "maxScreenAirTemp": 15.692299,
            "minScreenAirTemp": 15.405723,
            "max10mWindGust": 9.51621,
            "significantWeatherCode": 7,
            "totalPrecipAmount": 0,
            "totalSnowAmount": 0,
            "windSpeed10m": 5.715116,
            "windDirectionFrom10m": 295,
            "windGustSpeed10m": 8.798986,
            "visibility": 22815,
            "mslp": 101390,
            "screenRelativeHumidity": 82.76764,
            "feelsLikeTemp": 13.4228735,
            "uvIndex": 0,
            "probOfPrecipitation": 8,
            "probOfSnow": 3,
            "probOfHeavySnow": 0,
            "probOfRain": 8,
            "probOfHeavyRain": 3,
            "probOfHail": 0,
            "probOfSferics": 0
          },
          {
            "time": "2020-09-29T03:00Z",
            "maxScreenAirTemp": 15.322308,
            "minScreenAirTemp": 15.131837,
            "max10mWindGust": 9.322293,
            "significantWeatherCode": 7,
            "totalPrecipAmount": 0,
            "totalSnowAmount": 0,
            "windSpeed10m": 5.2415204,
            "windDirectionFrom10m": 292,
            "windGustSpeed10m": 8.060665,
            "visibility": 19283,
            "mslp": 101417,
            "screenRelativeHumidity": 88.041145,
            "feelsLikeTemp": 13.4105835,
            "uvIndex": 1,
            "probOfPrecipitation": 7,
            "probOfSnow": 3,
            "probOfHeavySnow": 0,
            "probOfRain": 7,
            "probOfHeavyRain": 2,
            "probOfHail": 0,
            "probOfSferics": 0
          },
          {
            "time": "2020-09-29T06:00Z",
            "maxScreenAirTemp": 15.205859,
            "minScreenAirTemp": 14.883821,
            "max10mWindGust": 8.0145445,
            "significantWeatherCode": 7,
            "totalPrecipAmount": 0,
            "totalSnowAmount": 0,
            "windSpeed10m": 4.87051,
            "windDirectionFrom10m": 289,
            "windGustSpeed10m": 7.5019193,
            "visibility": 19290,
            "mslp": 101526,
            "screenRelativeHumidity": 88.689186,
            "feelsLikeTemp": 13.355909,
            "uvIndex": 1,
            "probOfPrecipitation": 8,
            "probOfSnow": 3,
            "probOfHeavySnow": 0,
            "probOfRain": 8,
            "probOfHeavyRain": 3,
            "probOfHail": 0,
            "probOfSferics": 0
          },
          {
            "time": "2020-09-29T09:00Z",
            "maxScreenAirTemp": 16.053795,
            "minScreenAirTemp": 15.70929,
            "max10mWindGust": 8.861322,
            "significantWeatherCode": 7,
            "totalPrecipAmount": 0,
            "totalSnowAmount": 0,
            "windSpeed10m": 5.067158,
            "windDirectionFrom10m": 283,
            "windGustSpeed10m": 8.28928,
            "visibility": 18430,
            "mslp": 101656,
            "screenRelativeHumidity": 79.75796,
            "feelsLikeTemp": 14.16352,
            "uvIndex": 2,
            "probOfPrecipitation": 10,
            "probOfSnow": 3,
            "probOfHeavySnow": 0,
            "probOfRain": 10,
            "probOfHeavyRain": 3,
            "probOfHail": 0,
            "probOfSferics": 1
          },
          {
            "time": "2020-09-29T12:00Z",
            "maxScreenAirTemp": 16.962631,
            "minScreenAirTemp": 16.31567,
            "max10mWindGust": 9.193808,
            "significantWeatherCode": 3,
            "totalPrecipAmount": 0,
            "totalSnowAmount": 0,
            "windSpeed10m": 4.983613,
            "windDirectionFrom10m": 284,
            "windGustSpeed10m": 8.745625,
            "visibility": 24978,
            "mslp": 101692,
            "screenRelativeHumidity": 72.68091,
            "feelsLikeTemp": 15.044728,
            "uvIndex": 3,
            "probOfPrecipitation": 7,
            "probOfSnow": 0,
            "probOfHeavySnow": 0,
            "probOfRain": 7,
            "probOfHeavyRain": 4,
            "probOfHail": 0,
            "probOfSferics": 1
          },
          {
            "time": "2020-09-29T15:00Z",
            "maxScreenAirTemp": 16.829844,
            "minScreenAirTemp": 16.664377,
            "max10mWindGust": 9.532911,
            "significantWeatherCode": 3,
            "totalPrecipAmount": 0,
            "totalSnowAmount": 0,
            "windSpeed10m": 4.399494,
            "windDirectionFrom10m": 289,
            "windGustSpeed10m": 7.457124,
            "visibility": 22799,
            "mslp": 101680,
            "screenRelativeHumidity": 73.47937,
            "feelsLikeTemp": 15.192164,
            "uvIndex": 1,
            "probOfPrecipitation": 10,
            "probOfSnow": 0,
            "probOfHeavySnow": 0,
            "probOfRain": 10,
            "probOfHeavyRain": 5,
            "probOfHail": 0,
            "probOfSferics": 0
          },
          {
            "time": "2020-09-29T18:00Z",
            "maxScreenAirTemp": 15.3984785,
            "minScreenAirTemp": 15.1717825,
            "max10mWindGust": 8.02017,
            "significantWeatherCode": 7,
            "totalPrecipAmount": 0,
            "totalSnowAmount": 0,
            "windSpeed10m": 3.6978433,
            "windDirectionFrom10m": 293,
            "windGustSpeed10m": 5.7733636,
            "visibility": 19986,
            "mslp": 101705,
            "screenRelativeHumidity": 85.04361,
            "feelsLikeTemp": 14.130124,
            "uvIndex": 0,
            "probOfPrecipitation": 6,
            "probOfSnow": 3,
            "probOfHeavySnow": 0,
            "probOfRain": 6,
            "probOfHeavyRain": 1,
            "probOfHail": 0,
            "probOfSferics": 0
          },
          {
            "time": "2020-09-29T21:00Z",
            "maxScreenAirTemp": 14.274519,
            "minScreenAirTemp": 13.908499,
            "max10mWindGust": 6.301747,
            "significantWeatherCode": 7,
            "totalPrecipAmount": 0,
            "totalSnowAmount": 0,
            "windSpeed10m": 3.4311624,
            "windDirectionFrom10m": 251,
            "windGustSpeed10m": 5.428837,
            "visibility": 20323,
            "mslp": 101700,
            "screenRelativeHumidity": 88.56062,
            "feelsLikeTemp": 13.197786,
            "uvIndex": 0,
            "probOfPrecipitation": 8,
            "probOfSnow": 3,
            "probOfHeavySnow": 0,
            "probOfRain": 8,
            "probOfHeavyRain": 2,
            "probOfHail": 0,
            "probOfSferics": 0
          },
          {
            "time": "2020-09-30T00:00Z",
            "maxScreenAirTemp": 13.153594,
            "minScreenAirTemp": 12.632662,
            "max10mWindGust": 5.8360972,
            "significantWeatherCode": 7,
            "totalPrecipAmount": 0,
            "totalSnowAmount": 0,
            "windSpeed10m": 3.5965667,
            "windDirectionFrom10m": 213,
            "windGustSpeed10m": 5.6617436,
            "visibility": 19162,
            "mslp": 101623,
            "screenRelativeHumidity": 91.16041,
            "feelsLikeTemp": 11.659555,
            "uvIndex": 0,
            "probOfPrecipitation": 7,
            "probOfSnow": 3,
            "probOfHeavySnow": 0,
            "probOfRain": 7,
            "probOfHeavyRain": 2,
            "probOfHail": 0,
            "probOfSferics": 0
          },
          {
            "time": "2020-09-30T03:00Z",
            "maxScreenAirTemp": 12.1052685,
            "minScreenAirTemp": 11.918975,
            "max10mWindGust": 6.6520357,
            "significantWeatherCode": 9,
            "totalPrecipAmount": 0.18551606,
            "totalSnowAmount": 0,
            "windSpeed10m": 4.0214524,
            "windDirectionFrom10m": 212,
            "windGustSpeed10m": 6.2681932,
            "visibility": 16041,
            "mslp": 101514,
            "screenRelativeHumidity": 93.234406,
            "feelsLikeTemp": 10.389262,
            "uvIndex": 1,
            "probOfPrecipitation": 28,
            "probOfSnow": 0,
            "probOfHeavySnow": 0,
            "probOfRain": 28,
            "probOfHeavyRain": 14,
            "probOfHail": 0,
            "probOfSferics": 3
          },
          {
            "time": "2020-09-30T06:00Z",
            "maxScreenAirTemp": 12.186319,
            "minScreenAirTemp": 11.926584,
            "max10mWindGust": 7.112498,
            "significantWeatherCode": 7,
            "totalPrecipAmount": 0,
            "totalSnowAmount": 0,
            "windSpeed10m": 4.318734,
            "windDirectionFrom10m": 212,
            "windGustSpeed10m": 6.7411995,
            "visibility": 15265,
            "mslp": 101436,
            "screenRelativeHumidity": 93.8103,
            "feelsLikeTemp": 10.219198,
            "uvIndex": 1,
            "probOfPrecipitation": 12,
            "probOfSnow": 3,
            "probOfHeavySnow": 0,
            "probOfRain": 12,
            "probOfHeavyRain": 7,
            "probOfHail": 1,
            "probOfSferics": 1
          },
          {
            "time": "2020-09-30T09:00Z",
            "maxScreenAirTemp": 14.505345,
            "minScreenAirTemp": 14.379259,
            "max10mWindGust": 8.799397,
            "significantWeatherCode": 7,
            "totalPrecipAmount": 0,
            "totalSnowAmount": 0,
            "windSpeed10m": 5.25879,
            "windDirectionFrom10m": 206,
            "windGustSpeed10m": 8.796532,
            "visibility": 20213,
            "mslp": 101376,
            "screenRelativeHumidity": 83.08558,
            "feelsLikeTemp": 12.47135,
            "uvIndex": 2,
            "probOfPrecipitation": 9,
            "probOfSnow": 3,
            "probOfHeavySnow": 0,
            "probOfRain": 9,
            "probOfHeavyRain": 3,
            "probOfHail": 0,
            "probOfSferics": 1
          },
          {
            "time": "2020-09-30T12:00Z",
            "maxScreenAirTemp": 16.185167,
            "minScreenAirTemp": 15.472895,
            "max10mWindGust": 10.219562,
            "significantWeatherCode": 7,
            "totalPrecipAmount": 0,
            "totalSnowAmount": 0,
            "windSpeed10m": 5.7654757,
            "windDirectionFrom10m": 213,
            "windGustSpeed10m": 9.733222,
            "visibility": 23513,
            "mslp": 101253,
            "screenRelativeHumidity": 73.955154,
            "feelsLikeTemp": 13.739898,
            "uvIndex": 3,
            "probOfPrecipitation": 10,
            "probOfSnow": 3,
            "probOfHeavySnow": 0,
            "probOfRain": 10,
            "probOfHeavyRain": 4,
            "probOfHail": 0,
            "probOfSferics": 1
          },
          {
            "time": "2020-09-30T15:00Z",
            "maxScreenAirTemp": 16.621658,
            "minScreenAirTemp": 16.31002,
            "max10mWindGust": 10.62614,
            "significantWeatherCode": 7,
            "totalPrecipAmount": 0,
            "totalSnowAmount": 0,
            "windSpeed10m": 5.7918463,
            "windDirectionFrom10m": 204,
            "windGustSpeed10m": 9.563827,
            "visibility": 22298,
            "mslp": 101092,
            "screenRelativeHumidity": 73.23262,
            "feelsLikeTemp": 14.050428,
            "uvIndex": 1,
            "probOfPrecipitation": 11,
            "probOfSnow": 3,
            "probOfHeavySnow": 0,
            "probOfRain": 11,
            "probOfHeavyRain": 5,
            "probOfHail": 1,
            "probOfSferics": 1
          },
          {
            "time": "2020-09-30T18:00Z",
            "maxScreenAirTemp": 15.011768,
            "minScreenAirTemp": 14.850969,
            "max10mWindGust": 10.138191,
            "significantWeatherCode": 9,
            "totalPrecipAmount": 0.35787225,
            "totalSnowAmount": 0,
            "windSpeed10m": 5.8307037,
            "windDirectionFrom10m": 198,
            "windGustSpeed10m": 9.102428,
            "visibility": 18279,
            "mslp": 100996,
            "screenRelativeHumidity": 83.7981,
            "feelsLikeTemp": 12.679376,
            "uvIndex": 0,
            "probOfPrecipitation": 38,
            "probOfSnow": 0,
            "probOfHeavySnow": 0,
            "probOfRain": 38,
            "probOfHeavyRain": 25,
            "probOfHail": 3,
            "probOfSferics": 6
          },
          {
            "time": "2020-09-30T21:00Z",
            "maxScreenAirTemp": 14.032113,
            "minScreenAirTemp": 13.961067,
            "max10mWindGust": 9.967134,
            "significantWeatherCode": 7,
            "totalPrecipAmount": 0,
            "totalSnowAmount": 0,
            "windSpeed10m": 6.2278476,
            "windDirectionFrom10m": 193,
            "windGustSpeed10m": 9.80824,
            "visibility": 16042,
            "mslp": 100886,
            "screenRelativeHumidity": 88.15263,
            "feelsLikeTemp": 11.60044,
            "uvIndex": 0,
            "probOfPrecipitation": 18,
            "probOfSnow": 3,
            "probOfHeavySnow": 0,
            "probOfRain": 18,
            "probOfHeavyRain": 8,
            "probOfHail": 0,
            "probOfSferics": 1
          },
          {
            "time": "2020-10-01T00:00Z",
            "maxScreenAirTemp": 13.772767,
            "minScreenAirTemp": 13.470817,
            "max10mWindGust": 10.862982,
            "significantWeatherCode": 7,
            "totalPrecipAmount": 0,
            "totalSnowAmount": 0,
            "windSpeed10m": 6.454446,
            "windDirectionFrom10m": 198,
            "windGustSpeed10m": 10.251145,
            "visibility": 15133,
            "mslp": 100731,
            "screenRelativeHumidity": 90.11494,
            "feelsLikeTemp": 11.041478,
            "uvIndex": 0,
            "probOfPrecipitation": 15,
            "probOfSnow": 3,
            "probOfHeavySnow": 0,
            "probOfRain": 15,
            "probOfHeavyRain": 7,
            "probOfHail": 0,
            "probOfSferics": 1
          },
          {
            "time": "2020-10-01T03:00Z",
            "maxScreenAirTemp": 13.199588,
            "minScreenAirTemp": 13.044476,
            "max10mWindGust": 10.846993,
            "significantWeatherCode": 7,
            "totalPrecipAmount": 0,
            "totalSnowAmount": 0,
            "windSpeed10m": 6.6610675,
            "windDirectionFrom10m": 202,
            "windGustSpeed10m": 10.565591,
            "visibility": 15327,
            "mslp": 100565,
            "screenRelativeHumidity": 91.10098,
            "feelsLikeTemp": 10.522679,
            "uvIndex": 1,
            "probOfPrecipitation": 14,
            "probOfSnow": 3,
            "probOfHeavySnow": 0,
            "probOfRain": 14,
            "probOfHeavyRain": 6,
            "probOfHail": 1,
            "probOfSferics": 1
          },
          {
            "time": "2020-10-01T06:00Z",
            "maxScreenAirTemp": 12.779707,
            "minScreenAirTemp": 12.687179,
            "max10mWindGust": 11.480693,
            "significantWeatherCode": 7,
            "totalPrecipAmount": 0,
            "totalSnowAmount": 0,
            "windSpeed10m": 6.810104,
            "windDirectionFrom10m": 206,
            "windGustSpeed10m": 10.855111,
            "visibility": 14025,
            "mslp": 100446,
            "screenRelativeHumidity": 91.786476,
            "feelsLikeTemp": 10.025434,
            "uvIndex": 1,
            "probOfPrecipitation": 15,
            "probOfSnow": 3,
            "probOfHeavySnow": 0,
            "probOfRain": 15,
            "probOfHeavyRain": 7,
            "probOfHail": 1,
            "probOfSferics": 1
          },
          {
            "time": "2020-10-01T09:00Z",
            "maxScreenAirTemp": 14.1435795,
            "minScreenAirTemp": 14.000349,
            "max10mWindGust": 13.11339,
            "significantWeatherCode": 10,
            "totalPrecipAmount": 0.65582985,
            "totalSnowAmount": 0,
            "windSpeed10m": 7.6085334,
            "windDirectionFrom10m": 206,
            "windGustSpeed10m": 12.61973,
            "visibility": 16419,
            "mslp": 100324,
            "screenRelativeHumidity": 86.18151,
            "feelsLikeTemp": 11.127154,
            "uvIndex": 2,
            "probOfPrecipitation": 36,
            "probOfSnow": 0,
            "probOfHeavySnow": 0,
            "probOfRain": 36,
            "probOfHeavyRain": 20,
            "probOfHail": 1,
            "probOfSferics": 4
          },
          {
            "time": "2020-10-01T12:00Z",
            "maxScreenAirTemp": 15.816573,
            "minScreenAirTemp": 15.745004,
            "max10mWindGust": 15.400595,
            "significantWeatherCode": 10,
            "totalPrecipAmount": 1.3162712,
            "totalSnowAmount": 0,
            "windSpeed10m": 8.779684,
            "windDirectionFrom10m": 215,
            "windGustSpeed10m": 14.743919,
            "visibility": 16365,
            "mslp": 100192,
            "screenRelativeHumidity": 78.08449,
            "feelsLikeTemp": 12.136593,
            "uvIndex": 2,
            "probOfPrecipitation": 44,
            "probOfSnow": 0,
            "probOfHeavySnow": 0,
            "probOfRain": 44,
            "probOfHeavyRain": 29,
            "probOfHail": 3,
            "probOfSferics": 6
          },
          {
            "time": "2020-10-01T15:00Z",
            "maxScreenAirTemp": 15.524376,
            "minScreenAirTemp": 15.29316,
            "max10mWindGust": 15.183107,
            "significantWeatherCode": 12,
            "totalPrecipAmount": 1.4067549,
            "totalSnowAmount": 0,
            "windSpeed10m": 8.238106,
            "windDirectionFrom10m": 214,
            "windGustSpeed10m": 13.463846,
            "visibility": 15765,
            "mslp": 100075,
            "screenRelativeHumidity": 80.53263,
            "feelsLikeTemp": 12.067332,
            "uvIndex": 1,
            "probOfPrecipitation": 59,
            "probOfSnow": 0,
            "probOfHeavySnow": 0,
            "probOfRain": 58,
            "probOfHeavyRain": 40,
            "probOfHail": 5,
            "probOfSferics": 5
          },
          {
            "time": "2020-10-01T18:00Z",
            "maxScreenAirTemp": 14.8389015,
            "minScreenAirTemp": 14.627806,
            "max10mWindGust": 14.108059,
            "significantWeatherCode": 9,
            "totalPrecipAmount": 1.1329805,
            "totalSnowAmount": 0,
            "windSpeed10m": 8.083032,
            "windDirectionFrom10m": 217,
            "windGustSpeed10m": 12.9976635,
            "visibility": 18093,
            "mslp": 100017,
            "screenRelativeHumidity": 83.347824,
            "feelsLikeTemp": 11.532052,
            "uvIndex": 0,
            "probOfPrecipitation": 43,
            "probOfSnow": 0,
            "probOfHeavySnow": 0,
            "probOfRain": 43,
            "probOfHeavyRain": 27,
            "probOfHail": 3,
            "probOfSferics": 6
          },
          {
            "time": "2020-10-01T21:00Z",
            "maxScreenAirTemp": 14.427901,
            "minScreenAirTemp": 14.294515,
            "max10mWindGust": 14.235062,
            "significantWeatherCode": 9,
            "totalPrecipAmount": 0.6538835,
            "totalSnowAmount": 0,
            "windSpeed10m": 8.449903,
            "windDirectionFrom10m": 228,
            "windGustSpeed10m": 13.456639,
            "visibility": 18832,
            "mslp": 100024,
            "screenRelativeHumidity": 82.89305,
            "feelsLikeTemp": 10.954682,
            "uvIndex": 0,
            "probOfPrecipitation": 35,
            "probOfSnow": 0,
            "probOfHeavySnow": 0,
            "probOfRain": 35,
            "probOfHeavyRain": 21,
            "probOfHail": 2,
            "probOfSferics": 9
          },
          {
            "time": "2020-10-02T00:00Z",
            "maxScreenAirTemp": 13.875574,
            "minScreenAirTemp": 13.7938385,
            "max10mWindGust": 13.884269,
            "significantWeatherCode": 7,
            "totalPrecipAmount": 0,
            "totalSnowAmount": 0,
            "windSpeed10m": 8.258209,
            "windDirectionFrom10m": 228,
            "windGustSpeed10m": 13.202748,
            "visibility": 18185,
            "mslp": 99993,
            "screenRelativeHumidity": 83.0442,
            "feelsLikeTemp": 10.579348,
            "uvIndex": 0,
            "probOfPrecipitation": 17,
            "probOfSnow": 3,
            "probOfHeavySnow": 0,
            "probOfRain": 17,
            "probOfHeavyRain": 10,
            "probOfHail": 2,
            "probOfSferics": 6
          },
          {
            "time": "2020-10-02T03:00Z",
            "maxScreenAirTemp": 13.18002,
            "minScreenAirTemp": 13.067205,
            "max10mWindGust": 13.245719,
            "significantWeatherCode": 7,
            "totalPrecipAmount": 0,
            "totalSnowAmount": 0,
            "windSpeed10m": 7.9227514,
            "windDirectionFrom10m": 221,
            "windGustSpeed10m": 12.721969,
            "visibility": 19050,
            "mslp": 99955,
            "screenRelativeHumidity": 83.74947,
            "feelsLikeTemp": 9.97823,
            "uvIndex": 0,
            "probOfPrecipitation": 12,
            "probOfSnow": 3,
            "probOfHeavySnow": 0,
            "probOfRain": 12,
            "probOfHeavyRain": 6,
            "probOfHail": 1,
            "probOfSferics": 2
          },
          {
            "time": "2020-10-02T06:00Z",
            "maxScreenAirTemp": 12.63561,
            "minScreenAirTemp": 12.430864,
            "max10mWindGust": 13.074626,
            "significantWeatherCode": 3,
            "totalPrecipAmount": 0,
            "totalSnowAmount": 0,
            "windSpeed10m": 7.6822267,
            "windDirectionFrom10m": 213,
            "windGustSpeed10m": 12.288319,
            "visibility": 19416,
            "mslp": 99957,
            "screenRelativeHumidity": 85.88039,
            "feelsLikeTemp": 9.455343,
            "uvIndex": 1,
            "probOfPrecipitation": 7,
            "probOfSnow": 0,
            "probOfHeavySnow": 0,
            "probOfRain": 7,
            "probOfHeavyRain": 5,
            "probOfHail": 1,
            "probOfSferics": 2
          },
          {
            "time": "2020-10-02T09:00Z",
            "maxScreenAirTemp": 13.892644,
            "minScreenAirTemp": 13.65314,
            "max10mWindGust": 13.895945,
            "significantWeatherCode": 7,
            "totalPrecipAmount": 0,
            "totalSnowAmount": 0,
            "windSpeed10m": 8.174398,
            "windDirectionFrom10m": 216,
            "windGustSpeed10m": 13.438968,
            "visibility": 21062,
            "mslp": 99977,
            "screenRelativeHumidity": 79.10733,
            "feelsLikeTemp": 10.59863,
            "uvIndex": 2,
            "probOfPrecipitation": 11,
            "probOfSnow": 3,
            "probOfHeavySnow": 0,
            "probOfRain": 11,
            "probOfHeavyRain": 5,
            "probOfHail": 1,
            "probOfSferics": 1
          },
          {
            "time": "2020-10-02T12:00Z",
            "maxScreenAirTemp": 15.385403,
            "minScreenAirTemp": 15.261491,
            "max10mWindGust": 14.480871,
            "significantWeatherCode": 7,
            "totalPrecipAmount": 0,
            "totalSnowAmount": 0,
            "windSpeed10m": 8.396146,
            "windDirectionFrom10m": 217,
            "windGustSpeed10m": 14.039768,
            "visibility": 21761,
            "mslp": 99950,
            "screenRelativeHumidity": 70.0675,
            "feelsLikeTemp": 11.729583,
            "uvIndex": 2,
            "probOfPrecipitation": 16,
            "probOfSnow": 3,
            "probOfHeavySnow": 0,
            "probOfRain": 16,
            "probOfHeavyRain": 8,
            "probOfHail": 1,
            "probOfSferics": 2
          },
          {
            "time": "2020-10-02T15:00Z",
            "maxScreenAirTemp": 15.190587,
            "minScreenAirTemp": 14.954988,
            "max10mWindGust": 13.7924,
            "significantWeatherCode": 10,
            "totalPrecipAmount": 0.50839996,
            "totalSnowAmount": 0,
            "windSpeed10m": 7.5473294,
            "windDirectionFrom10m": 216,
            "windGustSpeed10m": 12.47752,
            "visibility": 21873,
            "mslp": 99877,
            "screenRelativeHumidity": 71.41744,
            "feelsLikeTemp": 11.888186,
            "uvIndex": 1,
            "probOfPrecipitation": 34,
            "probOfSnow": 0,
            "probOfHeavySnow": 0,
            "probOfRain": 34,
            "probOfHeavyRain": 19,
            "probOfHail": 1,
            "probOfSferics": 5
          },
          {
            "time": "2020-10-02T18:00Z",
            "maxScreenAirTemp": 13.982371,
            "minScreenAirTemp": 13.659171,
            "max10mWindGust": 12.6104,
            "significantWeatherCode": 7,
            "totalPrecipAmount": 0,
            "totalSnowAmount": 0,
            "windSpeed10m": 7.1149807,
            "windDirectionFrom10m": 205,
            "windGustSpeed10m": 11.402956,
            "visibility": 20848,
            "mslp": 99885,
            "screenRelativeHumidity": 79.048515,
            "feelsLikeTemp": 10.978907,
            "uvIndex": 0,
            "probOfPrecipitation": 19,
            "probOfSnow": 3,
            "probOfHeavySnow": 0,
            "probOfRain": 18,
            "probOfHeavyRain": 10,
            "probOfHail": 2,
            "probOfSferics": 3
          }
        ]
      }
    }
  ],
  "parameters": [
    {
      "totalSnowAmount": {
        "type": "Parameter",
        "description": "Total Snow Amount Over Previous Three Hours",
        "unit": {
          "label": "millimetres",
          "symbol": {
            "value": "http://www.opengis.net/def/uom/UCUM/",
            "type": "mm"
          }
        }
      },
      "visibility": {
        "type": "Parameter",
        "description": "Visibility Over Previous Three Hours",
        "unit": {
          "label": "metres",
          "symbol": {
            "value": "http://www.opengis.net/def/uom/UCUM/",
            "type": "m"
          }
        }
      },
      "probOfHail": {
        "type": "Parameter",
        "description": "Three Hour Probability of Hail",
        "unit": {
          "label": "percentage",
          "symbol": {
            "value": "http://www.opengis.net/def/uom/UCUM/",
            "type": "%"
          }
        }
      },
      "probOfHeavyRain": {
        "type": "Parameter",
        "description": "Three Hour Probability of Heavy Rain",
        "unit": {
          "label": "percentage",
          "symbol": {
            "value": "http://www.opengis.net/def/uom/UCUM/",
            "type": "%"
          }
        }
      },
      "windDirectionFrom10m": {
        "type": "Parameter",
        "description": "10m Wind From Direction Over Previous Three Hours",
        "unit": {
          "label": "degrees",
          "symbol": {
            "value": "http://www.opengis.net/def/uom/UCUM/",
            "type": "deg"
          }
        }
      },
      "maxScreenAirTemp": {
        "type": "Parameter",
        "description": "Maximum Screen Air Temperature Over Previous Three Hours",
        "unit": {
          "label": "degrees Celsius",
          "symbol": {
            "value": "http://www.opengis.net/def/uom/UCUM/",
            "type": "Cel"
          }
        }
      },
      "feelsLikeTemp": {
        "type": "Parameter",
        "description": "Feels Like Temperature Over Previous Three Hours",
        "unit": {
          "label": "degrees Celsius",
          "symbol": {
            "value": "http://www.opengis.net/def/uom/UCUM/",
            "type": "Cel"
          }
        }
      },
      "probOfSferics": {
        "type": "Parameter",
        "description": "Three Hour Probability of Sferics",
        "unit": {
          "label": "percentage",
          "symbol": {
            "value": "http://www.opengis.net/def/uom/UCUM/",
            "type": "%"
          }
        }
      },
      "screenRelativeHumidity": {
        "type": "Parameter",
        "description": "Screen Relative Humidity Over Previous Three Hours",
        "unit": {
          "label": "percentage",
          "symbol": {
            "value": "http://www.opengis.net/def/uom/UCUM/",
            "type": "%"
          }
        }
      },
      "probOfPrecipitation": {
        "type": "Parameter",
        "description": "Three Hour Probability of Precipitation",
        "unit": {
          "label": "percentage",
          "symbol": {
            "value": "http://www.opengis.net/def/uom/UCUM/",
            "type": "%"
          }
        }
      },
      "windSpeed10m": {
        "type": "Parameter",
        "description": "10m Wind Speed Over Previous Three Hours",
        "unit": {
          "label": "metres per second",
          "symbol": {
            "value": "http://www.opengis.net/def/uom/UCUM/",
            "type": "m/s"
          }
        }
      },
      "probOfRain": {
        "type": "Parameter",
        "description": "Three Hour Probability of Rain",
        "unit": {
          "label": "percentage",
          "symbol": {
            "value": "http://www.opengis.net/def/uom/UCUM/",
            "type": "%"
          }
        }
      },
      "max10mWindGust": {
        "type": "Parameter",
        "description": "Maximum 10m Wind Gust Speed Over Previous Three Hours",
        "unit": {
          "label": "metres per second",
          "symbol": {
            "value": "http://www.opengis.net/def/uom/UCUM/",
            "type": "m/s"
          }
        }
      },
      "significantWeatherCode": {
        "type": "Parameter",
        "description": "Three Hour Significant Weather Code",
        "unit": {
          "label": "dimensionless",
          "symbol": {
            "value": "https://metoffice.apiconnect.ibmcloud.com/metoffice/production/",
            "type": "1"
          }
        }
      },
      "probOfHeavySnow": {
        "type": "Parameter",
        "description": "Three Hour Probability of Heavy Snow",
        "unit": {
          "label": "percentage",
          "symbol": {
            "value": "http://www.opengis.net/def/uom/UCUM/",
            "type": "%"
          }
        }
      },
      "totalPrecipAmount": {
        "type": "Parameter",
        "description": "Total Precipitation Amount Over Previous Three Hours",
        "unit": {
          "label": "millimetres",
          "symbol": {
            "value": "http://www.opengis.net/def/uom/UCUM/",
            "type": "mm"
          }
        }
      },
      "minScreenAirTemp": {
        "type": "Parameter",
        "description": "Minimum Screen Air Temperature Over Previous Three Hours",
        "unit": {
          "label": "degrees Celsius",
          "symbol": {
            "value": "http://www.opengis.net/def/uom/UCUM/",
            "type": "Cel"
          }
        }
      },
      "mslp": {
        "type": "Parameter",
        "description": "Mean Sea Level Pressure Over Previous Three Hours",
        "unit": {
          "label": "pascals",
          "symbol": {
            "value": "http://www.opengis.net/def/uom/UCUM/",
            "type": "Pa"
          }
        }
      },
      "windGustSpeed10m": {
        "type": "Parameter",
        "description": "10m Wind Gust Speed Over Previous Three Hours",
        "unit": {
          "label": "metres per second",
          "symbol": {
            "value": "http://www.opengis.net/def/uom/UCUM/",
            "type": "m/s"
          }
        }
      },
      "probOfSnow": {
        "type": "Parameter",
        "description": "Three Hour Probability of Snow",
        "unit": {
          "label": "percentage",
          "symbol": {
            "value": "http://www.opengis.net/def/uom/UCUM/",
            "type": "%"
          }
        }
      },
      "uvIndex": {
        "type": "Parameter",
        "description": "Maximum UV Index Over Previous Three Hours",
        "unit": {
          "label": "dimensionless",
          "symbol": {
            "value": "http://www.opengis.net/def/uom/UCUM/",
            "type": "1"
          }
        }
      }
    }
  ]
}
